artifact_hub/__init__.py
artifact_hub/requirements.txt
artifact_hub/backends/__init__.py
artifact_hub/backends/base_backend.py
artifact_hub/backends/s3_backend.py
artifact_hub/history_backends/__init__.py
artifact_hub/history_backends/history_base_backend.py
artifact_hub/history_backends/history_s3_backend.py
artifact_hub-0.0.3.dist-info/METADATA
artifact_hub-0.0.3.dist-info/WHEEL
artifact_hub-0.0.3.dist-info/licenses/LICENSE
artifact_hub-0.0.3.dist-info/RECORD
