Metadata-Version: 2.1
Name: artifact-hub
Version: 0.0.3
Summary: Use object storage as a self hosted hub
Project-URL: Homepage, https://https://github.com/robotstech/artifact-hub
Project-URL: Repository, https://https://github.com/robotstech/artifact-hub.git
Project-URL: Bug Tracker, https://github.com/robotstech/artifact-hub/issues
Author-email: iamr0b0tx <tech@robotslimited.com>
Maintainer-email: iamr0b0tx <tech@robotslimited.com>
License: MIT License
License-File: LICENSE
Keywords: artifacts,hub,storage
Classifier: Environment :: Console
Classifier: Intended Audience :: Developers
Classifier: Intended Audience :: Education
Classifier: Intended Audience :: Information Technology
Classifier: Intended Audience :: Science/Research
Classifier: License :: OSI Approved :: MIT License
Classifier: Natural Language :: English
Classifier: Operating System :: OS Independent
Classifier: Programming Language :: Python :: 3.7
Classifier: Programming Language :: Python :: 3.8
Classifier: Programming Language :: Python :: 3.9
Requires-Python: >=3.7
Requires-Dist: boto3>=1.26.89
Provides-Extra: web
Requires-Dist: fastapi>=0.94.0; extra == 'web'
Requires-Dist: uvicorn[standard]>=0.21.0; extra == 'web'
